{
    "request_status": "completed",
    "notes": "",
    "reminder_period": 5,
    "owner_id": "130808000000008003",
    "description": "",
    "request_name": "22F-M999-Student Contract - St. Clair College Ace Acumen Program",
    "modified_time": 1665587724603,
    "action_time": 1665698882494,
    "is_deleted": "False",
    "expiration_days": 15,
    "is_sequential": "True",
    "sign_submitted_time": 1665587724644,
    "owner_first_name": "Amit",
    "sign_percentage": 100,
    "expire_by": 1666929540000,
    "owner_email": "amit.jain@canadaacumen.ca",
    "created_time": 1665587670746,
    "email_reminders": "True",
    "document_ids": [
        {
            "document_name": "22F-M999-Student Contract - St. Clair College Ace Acumen Program",
            "document_size": 458875,
            "document_order": "0",
            "is_editable": "False",
            "total_pages": 8,
            "document_id": "130808000003585115"
        }
    ],
    "self_sign": "False",
    "in_process": "False",
    "validity": -1,
    "request_type_name": "Others",
    "request_id": "130808000003585129",
    "zsdocumentid": "XAHKMIJOR8J6UGJWLHX6TECL0KETJT9STHKGE7BGFI0",
    "request_type_id": "130808000000000135",
    "owner_last_name": "Jain",
    "actions": [
        {
            "verify_recipient": "False",
            "recipient_countrycode_iso": "",
            "action_type": "SIGN",
            "private_notes": "",
            "cloud_provider_name": "Zoho Sign",
            "has_payment": "False",
            "recipient_email": "ak784@myscc.ca",
            "send_completed_document": "True",
            "allow_signing": "False",
            "recipient_phonenumber": "",
            "is_bulk": "False",
            "action_id": "130808000003585132",
            "is_revoked": "False",
            "is_embedded": "False",
            "cloud_provider_id": 10,
            "signing_order": 1,
            "recipient_name": "Kumar,Akshay",
            "delivery_mode": "EMAIL",
            "action_status": "SIGNED",
            "recipient_countrycode": ""
        }
    ]
}